deps_manager/__init__.py
deps_manager/dependencies.py
deps_manager/main.py
deps_manager/utils.py
deps_manager-1.0.12.dist-info/METADATA
deps_manager-1.0.12.dist-info/WHEEL
deps_manager-1.0.12.dist-info/entry_points.txt
deps_manager-1.0.12.dist-info/top_level.txt
deps_manager-1.0.12.dist-info/RECORD
