Metadata-Version: 2.1
Name: deps-manager
Version: 1.0.12
Author: Harshada Tupe
Author-email: harshadatupe8@gmail.com
License: MIT
Classifier: Programming Language :: Python :: 3 :: Only
Classifier: Operating System :: OS Independent
Requires-Python: >=3.8
Requires-Dist: click
Requires-Dist: conan
Requires-Dist: pipreqs
